ingress/__init__.py
ingress/caddy.py
ingress/cli.py
ingress/config.py
ingress/exceptions.py
ingress/main.py
ingress/models.py
ingress/repo.py
ingress/templates/Caddyfile
ingress/templates/__init__.py
ingress/utils.py
hukudo_ingress-3.2.1.dist-info/licenses/LICENSE
hukudo_ingress-3.2.1.dist-info/WHEEL
hukudo_ingress-3.2.1.dist-info/entry_points.txt
hukudo_ingress-3.2.1.dist-info/METADATA
hukudo_ingress-3.2.1.dist-info/RECORD
