Metadata-Version: 2.4
Name: hukudo-ingress
Version: 3.2.1
Author: hukudo GmbH
Author-email: hukudo GmbH <hukudo-ingress@hukudo.de>
License-File: LICENSE
Classifier: Programming Language :: Python :: 3
Requires-Dist: backoff
Requires-Dist: click
Requires-Dist: docker
Requires-Dist: httpx
Requires-Dist: ipython
Requires-Dist: jinja2
Requires-Dist: logfmter
Requires-Python: >=3.11
Project-URL: Homepage, https://gitlab.com/hukudo/ingress
